mdformat_vuepress/__init__.py
mdformat_vuepress/plugin.py
mdformat_vuepress-0.1.0.dist-info/METADATA
mdformat_vuepress-0.1.0.dist-info/WHEEL
mdformat_vuepress-0.1.0.dist-info/entry_points.txt
mdformat_vuepress-0.1.0.dist-info/licenses/LICENSE
mdformat_vuepress-0.1.0.dist-info/RECORD
