Metadata-Version: 2.4
Name: mdformat-vuepress
Version: 0.1.0
Summary: Preserve VuePress-style ::: containers in mdformat
Author-email: Marius Högger <marius.hoegger@hotmail.com>
License: MIT License
License-File: LICENSE
Keywords: formatter,markdown,mdformat,vuepress
Classifier: Development Status :: 4 - Beta
Classifier: Intended Audience :: Developers
Classifier: License :: OSI Approved :: MIT License
Classifier: Programming Language :: Python :: 3
Classifier: Programming Language :: Python :: 3.9
Classifier: Programming Language :: Python :: 3.10
Classifier: Programming Language :: Python :: 3.11
Classifier: Programming Language :: Python :: 3.12
Classifier: Topic :: Software Development :: Libraries :: Python Modules
Classifier: Topic :: Text Processing :: Markup
Requires-Python: >=3.9
Requires-Dist: markdown-it-py>=3
Requires-Dist: mdformat>=0.7
Requires-Dist: mdit-py-plugins>=0.4
Provides-Extra: test
Requires-Dist: pytest-cov; extra == 'test'
Requires-Dist: pytest>=6.0; extra == 'test'
